co2br/__init__.py
co2br/pvtx.py
co2br/solubility.py
co2br/viscosity.py
CO2Br-0.1.dist-info/METADATA
CO2Br-0.1.dist-info/WHEEL
CO2Br-0.1.dist-info/top_level.txt
CO2Br-0.1.dist-info/RECORD
