Metadata-Version: 2.2
Name: CO2Br
Version: 0.1
Author: Sayan Sen
Dynamic: author
Dynamic: description
Dynamic: description-content-type
